{
  "collectionId": "ontario-stores",
  "displayName": "Ontario Ashley HomeStore Locations",
  "description": "TDG-owned Ashley HomeStore participating locations in Ontario, Canada",
  "locations": [
    {
      "id": "barrie",
      "city": "Barrie",
      "storeName": "Barrie Ashley HomeStore",
      "address": "30 North Village Way, Unit 4",
      "storePhone": "+17057287838",
      "customerServicePhone": "+18007373233",
      "websiteUrl": "https://www.ashleyfurniture.com/store/ca/ontario/barrie/9000092867/",
      "coordinates": {
        "lat": 44.3894,
        "lng": -79.6903
      }
    },
    {
      "id": "brampton",
      "city": "Brampton",
      "storeName": "Brampton Ashley HomeStore",
      "address": "70 Great Lakes Dr, Unit 149",
      "storePhone": "+19057993284",
      "customerServicePhone": "+18007373233",
      "websiteUrl": "https://www.ashleyfurniture.com/store/ca/ontario/brampton/7710000520/",
      "coordinates": {
        "lat": 43.7315,
        "lng": -79.7624
      }
    },
    {
      "id": "brantford",
      "city": "Brantford",
      "storeName": "Brantford Ashley HomeStore",
      "address": "184 Lynden Rd",
      "storePhone": "+12262500138",
      "customerServicePhone": "+12262500138",
      "websiteUrl": "https://www.ashleyfurniture.com/store/ca/ontario/brantford/7710000521/",
      "coordinates": {
        "lat": 43.1394,
        "lng": -80.2644
      }
    },
    {
      "id": "burlington",
      "city": "Burlington",
      "storeName": "Burlington Ashley HomeStore",
      "address": "7-3060 Davidson Court",
      "storePhone": "+19053151700",
      "customerServicePhone": "+18007373233",
      "websiteUrl": "https://www.ashleyfurniture.com/store/ca/ontario/burlington/7710000538/",
      "coordinates": {
        "lat": 43.3255,
        "lng": -79.7990
      }
    },
    {
      "id": "guelph",
      "city": "Guelph",
      "storeName": "Guelph Ashley HomeStore",
      "address": "389 Woodlawn Rd W",
      "storePhone": "+12267801373",
      "customerServicePhone": null,
      "websiteUrl": "https://www.ashleyfurniture.com/store/ca/ontario/guelph/9000187972/",
      "coordinates": {
        "lat": 43.5448,
        "lng": -80.2482
      }
    },
    {
      "id": "kitchener",
      "city": "Kitchener",
      "storeName": "Kitchener Ashley HomeStore",
      "address": "D2-655 Fairway Rd S",
      "storePhone": "+15198939595",
      "customerServicePhone": null,
      "websiteUrl": "https://www.ashleyfurniture.com/store/ca/ontario/kitchener/9000749061/",
      "coordinates": {
        "lat": 43.4168,
        "lng": -80.4883
      }
    },
    {
      "id": "london",
      "city": "London",
      "storeName": "London Ashley HomeStore",
      "address": "3325 Wonderland Rd South, Unit 1",
      "storePhone": "+15196521637",
      "customerServicePhone": "+18007373233",
      "websiteUrl": "https://www.ashleyfurniture.com/store/ca/ontario/london/9000185634/",
      "coordinates": {
        "lat": 42.9490,
        "lng": -81.2760
      }
    },
    {
      "id": "mississauga-mavis",
      "city": "Mississauga",
      "storeName": "Mississauga Ashley HomeStore",
      "address": "5900 Mavis Rd, Unit 2",
      "storePhone": "+15877602789",
      "customerServicePhone": null,
      "websiteUrl": "https://www.ashleyfurniture.com/store/ca/ontario/mississauga/7710000523/",
      "coordinates": {
        "lat": 43.6205,
        "lng": -79.6525
      }
    },
    {
      "id": "mississauga-matheson",
      "city": "Mississauga",
      "storeName": "Mississauga Ashley Clearance Centre",
      "address": "333 Matheson Blvd W",
      "storePhone": "+19057129846",
      "customerServicePhone": null,
      "websiteUrl": "https://www.ashleyfurniture.com/store/ca/ontario/mississauga/9000482012/",
      "coordinates": {
        "lat": 43.6629,
        "lng": -79.6127
      }
    },
    {
      "id": "newmarket",
      "city": "Newmarket",
      "storeName": "Newmarket Ashley HomeStore",
      "address": "17700 Yonge Street",
      "storePhone": "+12893192770",
      "customerServicePhone": "+18007373233",
      "websiteUrl": "https://www.ashleyfurniture.com/store/ca/ontario/newmarket/9000200389/",
      "coordinates": {
        "lat": 44.0592,
        "lng": -79.4613
      }
    },
    {
      "id": "ottawa",
      "city": "Ottawa",
      "storeName": "Ottawa Ashley HomeStore",
      "address": "530 West Hunt Club Rd",
      "storePhone": "+16132321441",
      "customerServicePhone": "+18007373233",
      "websiteUrl": "https://www.ashleyfurniture.com/store/ca/ontario/ottawa/9000064175/",
      "coordinates": {
        "lat": 45.3476,
        "lng": -75.6903
      }
    },
    {
      "id": "richmond-hill",
      "city": "Richmond Hill",
      "storeName": "Richmond Hill Ashley HomeStore",
      "address": "45 Red Maple Rd",
      "storePhone": "+19057636020",
      "customerServicePhone": "+18007373233",
      "websiteUrl": "https://www.ashleyfurniture.com/store/ca/ontario/richmond-hill/9000117873/",
      "coordinates": {
        "lat": 43.8828,
        "lng": -79.4403
      }
    },
    {
      "id": "scarborough",
      "city": "Scarborough",
      "storeName": "Scarborough Ashley HomeStore",
      "address": "23 William Kitchen Rd, H3",
      "storePhone": "+14162991098",
      "customerServicePhone": "+18007373233",
      "websiteUrl": "https://www.ashleyfurniture.com/store/ca/ontario/scarborough/9000092868/",
      "coordinates": {
        "lat": 43.7764,
        "lng": -79.2318
      }
    },
    {
      "id": "st-catharines",
      "city": "St. Catharines",
      "storeName": "St. Catharines Ashley HomeStore",
      "address": "285 Geneva St",
      "storePhone": "+16474278359",
      "customerServicePhone": null,
      "websiteUrl": "https://www.ashleyfurniture.com/store/ca/ontario/st-catharines/9000850197/",
      "coordinates": {
        "lat": 43.1594,
        "lng": -79.2469
      }
    },
    {
      "id": "stoney-creek",
      "city": "Stoney Creek",
      "storeName": "Stoney Creek Ashley HomeStore",
      "address": "1776 Stone Church Rd E, Unit 2",
      "storePhone": "+19056434646",
      "customerServicePhone": null,
      "websiteUrl": "https://www.ashleyfurniture.com/store/ca/ontario/stoney-creek/7710000526/",
      "coordinates": {
        "lat": 43.2075,
        "lng": -79.7441
      }
    },
    {
      "id": "toronto",
      "city": "Toronto",
      "storeName": "Toronto Ashley HomeStore",
      "address": "1602 The Queensway",
      "storePhone": "+16474263110",
      "customerServicePhone": null,
      "websiteUrl": "https://www.ashleyfurniture.com/store/ca/ontario/toronto/9000889922/",
      "coordinates": {
        "lat": 43.6205,
        "lng": -79.5132
      }
    },
    {
      "id": "vaughan",
      "city": "Vaughan",
      "storeName": "Vaughan Ashley HomeStore",
      "address": "7979 Weston Rd",
      "storePhone": "+16474273900",
      "customerServicePhone": null,
      "websiteUrl": "https://www.ashleyfurniture.com/store/ca/ontario/woodbridge/7710000527/",
      "coordinates": {
        "lat": 43.7942,
        "lng": -79.5932
      }
    },
    {
      "id": "whitby",
      "city": "Whitby",
      "storeName": "Whitby Ashley HomeStore",
      "address": "1650 Victoria St E, Unit 5A",
      "storePhone": "+19057234786",
      "customerServicePhone": null,
      "websiteUrl": "https://www.ashleyfurniture.com/store/ca/ontario/whitby/9000035147/",
      "coordinates": {
        "lat": 43.8971,
        "lng": -78.9091
      }
    },
    {
      "id": "windsor",
      "city": "Windsor",
      "storeName": "Windsor Ashley HomeStore",
      "address": "1-650 Division Rd",
      "storePhone": "+15199695814",
      "customerServicePhone": "+18007373233",
      "websiteUrl": "https://www.ashleyfurniture.com/store/ca/ontario/windsor/9000170257/",
      "coordinates": {
        "lat": 42.2879,
        "lng": -82.9877
      }
    }
  ],
  "metadata": {
    "createdAt": "2025-12-15T00:00:00.000Z",
    "updatedAt": "2026-04-16T00:00:00.000Z",
    "totalLocations": 19
  }
}
